typed_ffmpeg/__init__.py
typed_ffmpeg/_version.py
typed_ffmpeg/base.py
typed_ffmpeg/exceptions.py
typed_ffmpeg/expressions.py
typed_ffmpeg/filters.py
typed_ffmpeg/info.py
typed_ffmpeg/py.typed
typed_ffmpeg/schema.py
typed_ffmpeg/sources.py
typed_ffmpeg/types.py
typed_ffmpeg/codecs/__init__.py
typed_ffmpeg/codecs/decoders.py
typed_ffmpeg/codecs/encoders.py
typed_ffmpeg/codecs/schema.py
typed_ffmpeg/common/__init__.py
typed_ffmpeg/common/cache.py
typed_ffmpeg/common/schema.py
typed_ffmpeg/common/serialize.py
typed_ffmpeg/compile/__init__.py
typed_ffmpeg/compile/compile_cli.py
typed_ffmpeg/compile/compile_json.py
typed_ffmpeg/compile/compile_python.py
typed_ffmpeg/compile/context.py
typed_ffmpeg/compile/validate.py
typed_ffmpeg/dag/__init__.py
typed_ffmpeg/dag/factory.py
typed_ffmpeg/dag/nodes.py
typed_ffmpeg/dag/schema.py
typed_ffmpeg/dag/utils.py
typed_ffmpeg/dag/global_runnable/__init__.py
typed_ffmpeg/dag/global_runnable/global_args.py
typed_ffmpeg/dag/global_runnable/runnable.py
typed_ffmpeg/dag/io/__init__.py
typed_ffmpeg/dag/io/_input.py
typed_ffmpeg/dag/io/_output.py
typed_ffmpeg/dag/io/output_args.py
typed_ffmpeg/ffprobe/__init__.py
typed_ffmpeg/ffprobe/parse.py
typed_ffmpeg/ffprobe/probe.py
typed_ffmpeg/ffprobe/schema.py
typed_ffmpeg/ffprobe/xml2json.py
typed_ffmpeg/formats/__init__.py
typed_ffmpeg/formats/demuxers.py
typed_ffmpeg/formats/muxers.py
typed_ffmpeg/formats/schema.py
typed_ffmpeg/options/__init__.py
typed_ffmpeg/options/codec.py
typed_ffmpeg/options/format.py
typed_ffmpeg/options/framesync.py
typed_ffmpeg/options/timeline.py
typed_ffmpeg/streams/__init__.py
typed_ffmpeg/streams/audio.py
typed_ffmpeg/streams/av.py
typed_ffmpeg/streams/channel_layout.py
typed_ffmpeg/streams/subtitle.py
typed_ffmpeg/streams/video.py
typed_ffmpeg/utils/__init__.py
typed_ffmpeg/utils/escaping.py
typed_ffmpeg/utils/frozendict.py
typed_ffmpeg/utils/run.py
typed_ffmpeg/utils/snapshot.py
typed_ffmpeg/utils/typing.py
typed_ffmpeg/utils/view.py
typed_ffmpeg_compatible-3.11.dist-info/licenses/LICENSE
typed_ffmpeg_compatible-3.11.dist-info/METADATA
typed_ffmpeg_compatible-3.11.dist-info/WHEEL
typed_ffmpeg_compatible-3.11.dist-info/entry_points.txt
typed_ffmpeg_compatible-3.11.dist-info/top_level.txt
typed_ffmpeg_compatible-3.11.dist-info/RECORD
